Metadata-Version: 2.1
Name: theatro-cfg-loader
Version: 0.3.1
Summary: A library that allows to easily load configuration settings.
Home-page: https://github.com/nmvalera/cfg-loader
Author: Nicolas Maurice
Author-email: nicolas.maurice.valera@gmail.com
Maintainer: Jacob Floyd
Maintainer-email: cognifloyd@gmail.com
License: BSD-3-Clause
Platform: any
Classifier: Development Status :: 5 - Production/Stable
Classifier: Environment :: Web Environment
Classifier: Intended Audience :: Developers
Classifier: License :: OSI Approved :: BSD License
Classifier: Operating System :: OS Independent
Classifier: Programming Language :: Python
Classifier: Programming Language :: Python :: 3
Classifier: Programming Language :: Python :: 3.6
Classifier: Programming Language :: Python :: 3.7
Requires-Dist: marshmallow (>=3.0.0)
Requires-Dist: PyYAML (>=3.12)
Provides-Extra: dev
Requires-Dist: flake8 ; extra == 'dev'
Requires-Dist: autoflake ; extra == 'dev'
Requires-Dist: autopep8 ; extra == 'dev'
Requires-Dist: coverage ; extra == 'dev'
Requires-Dist: pytest (>=3) ; extra == 'dev'
Requires-Dist: tox ; extra == 'dev'
Requires-Dist: sphinx ; extra == 'dev'
Requires-Dist: sphinx-rtd-theme ; extra == 'dev'
Provides-Extra: doc
Requires-Dist: sphinx ; extra == 'doc'
Requires-Dist: sphinx-rtd-theme ; extra == 'doc'
